{
  "productos": [
    {
      "nombreProducto": "Estancia Mendoza",
      "precioProducto": "1800",
      "foto": "https://statics.dinoonline.com.ar/imagenes/full_600x600_ma/3061471_f.jpg",
      "categoria": "Cabernet",
      "id": 6
    },
    {
      "nombreProducto": "Enemigo",
      "precioProducto": "2100",
      "foto": "https://i.pinimg.com/736x/97/33/49/973349ce2edd57c29c9654a9eb73e14d.jpg",
      "categoria": "Malbec",
      "id": 8
    },
    {
      "nombreProducto": "Chateaux Margaux",
      "precioProducto": "3200",
      "foto": "https://media-verticommnetwork1.netdna-ssl.com/wines/chateau-margaux-1547686.jpg",
      "categoria": "Blend",
      "id": 9
    },
    {
      "nombreProducto": "Moncloa",
      "precioProducto": "3560",
      "foto": "https://hips.hearstapps.com/hmg-prod.s3.amazonaws.com/images/finca-moncloa-tintilla-de-rota-edicio-n-limitada-elle-1647171444.jpg?crop=1xw:1xh;center,top&resize=480:*",
      "categoria": "Bonarda",
      "id": 10
    },
    {
      "nombreProducto": "Luigi Bosca",
      "precioProducto": "2350",
      "foto": "https://http2.mlstatic.com/D_NQ_NP_989983-MLA44826831419_022021-O.webp",
      "categoria": "Tanat",
      "id": 11
    },
    {
      "nombreProducto": "Salentein",
      "precioProducto": "3150",
      "foto": "https://cepadevinos.com/wp-content/uploads/2016/09/Salentein-Reserve-Malbec-6X4-1.jpg",
      "categoria": "Cabernet",
      "id": 12
    }
  ]
}